README.rst
setup.py
libzbar/__init__.py
libzbar/_zbar.py
libzbar/zbar.py
libzbar_ctypes.egg-info/PKG-INFO
libzbar_ctypes.egg-info/SOURCES.txt
libzbar_ctypes.egg-info/dependency_links.txt
libzbar_ctypes.egg-info/top_level.txt