Metadata-Version: 1.1
Name: libzbar-ctypes
Version: 0.1.2
Summary: Python ctypes libzbar wrapper
Home-page: https://github.com/zaazbb/libzbar-ctypes
Author: zaazbb
Author-email: zaazbb@163.com
License: LGPL
Keywords: libzbar ctypes
Platform: UNKNOWN
Classifier: Development Status :: 3 - Alpha
Classifier: Intended Audience :: Developers
Classifier: Topic :: Multimedia :: Graphics :: Capture
Classifier: Topic :: Multimedia :: Graphics :: Capture :: Scanners
Classifier: Topic :: Multimedia :: Graphics :: Capture :: Screen Capture
Classifier: License :: Freeware
Classifier: Programming Language :: Python :: 2
Classifier: Programming Language :: Python :: 2.7
Classifier: Programming Language :: Python :: 3
Classifier: Programming Language :: Python :: 3.3
Classifier: Programming Language :: Python :: 3.4
Classifier: Programming Language :: Python :: 3.5
Classifier: Programming Language :: Python :: 3.6
Classifier: Operating System :: POSIX :: Linux
